{
  "youtube" : {
        "How to Improve your business with a Task Manager? Episode 1" : 45666,
        "It is your key to improve your business! Episode 2" : 65755,
        "How can public speaking change your life and business? Episode 3" : 97025,
        "5 tips for outstanding marketing! Episode 4" : 77375,
        "Unlocking your sales potential with Musk! Episode 5" : 36487,
        "How to stay motivated? Episode 6" : 57624,
        "Life hacks for successful pitching! Episode 7": 37519,
        "The art of negotiation: tips and techniques. Episode 8" : 35489,
        "How to develop public speaking skills? Episode 9" : 28139,
        "Why is analytics the key to success in business? Episode 10" : 28210,
        "FIVE steps: how to organize business processes? Episode 11" : 29711,
        "How to become an inspiring leader? Episode 12" : 30712,
        "4 steps to successful crowdfunding! Episode 13" : 32813,
        "How the Pareto principle changes your life and work? Episode 14" : 37814,
        "What you can learn from Elon Musk? Uncovering the secrets of success" : 1
    },
  "funds_keys" : [
      "diamonds",
      "oil_companies",
      "limited_edition_watches",
      "expensive_wine",
      "classic_cars",
      "pharmaceutical_companies",
      "car_rentals_in_dubai",
      "meme_tshirts",
      "real_estate_in_nigeria",
      "hamster_breeding",
      "artificial_intelligence",
      "electric_vehicle_manufacturers",
      "gold_mining_tools",
      "game_development",
      "space_companies",
      "unicorn_breeding",
      "onlyfans_models",
      "blockchain_projects"
    ],
  "2024-08-02": {
    "quiz":"wallet",
    "rebus":"profit",
    "funds":["space_companies","gold_mining_tools","oil_companies"]
  },
  "2024-08-03": {
    "quiz":"kyc",
    "rebus":"revenue",
    "funds":["blockchain_projects","artificial_intelligence","expensive_wine"]
  }
}
